Workbook
Name IQ_CH: 110000
Name IQ_CQ: 5000
Name IQ_CY: 10000
Name IQ_DAILY: 500000
Name IQ_FH: 100000
Name IQ_FQ: 500
Name IQ_FY: 1000
Name IQ_LTM: 2000
Name IQ_MONTH: 15000
Name IQ_NTM: 6000
Name IQ_WEEK: 50000
Name IQ_YTD: 3000

Sheet IS
A1: Microsoft Corp | Income Statement 10-Feb-2022 16:53
A3: Income Statement
A4: Annual Standardised in Millions of U.S. Dollars
C5: 2021 | D5: 2020 | E5: 2019 | F5: 2018 | G5: 2017
A6: Earnings Quality Score | C6: 86 | D6: 94 | E6: 85 | F6: 98 | G6: 88
A7: Period End Date | C7: 30-Jun-2021 | D7: 30-Jun-2020 | E7: 30-Jun-2019 | F7: 30-Jun-2018 | G7: 30-Jun-2017
A8: Original Announcement Date | C8: 27-Jul-2021 20:42 | D8: 22-Jul-2020 20:03 | E8: 18-Jul-2019 20:04 | F8: 19-Jul-2018 20:04 | G8: 19-Jul-2018 20:04
A9: Revenue | C9: 168088 | D9: 143015 | E9: 125843 | F9: 110360 | G9: 96571
A10: Net Sales | C10: 168088 | D10: 143015 | E10: 125843 | F10: 110360 | G10: 96571
A11: Other Revenue, Total | C11: -- | D11: -- | E11: -- | F11: -- | G11: --
A12: Total Revenue | C12: 168088 | D12: 143015 | E12: 125843 | F12: 110360 | G12: 96571
A13: Cost of Revenue, Total | C13: 52232 | D13: 46078 | E13: 42910 | F13: 38353 | G13: 34261
A14: Cost of Revenue | C14: 52232 | D14: 46078 | E14: 42910 | F14: 38353 | G14: 34261
A15: Gross Profit | C15: 115856 | D15: 96937 | E15: 82933 | F15: 72007 | G15: 62310
A17: Selling/General/Admin. Expenses, Total | C17: 25224 | D17: 24709 | E17: 23098 | F17: 22223 | G17: 18648
A18: Selling/General/Administrative Expense | C18: 23724 | D18: 23109 | E18: 21498 | F18: 20623 | G18: 17348
A19: Advertising Expense | C19: 1500 | D19: 1600 | E19: 1600 | F19: 1600 | G19: 1300
A20: Research & Development | C20: 20716 | D20: 19269 | E20: 16876 | F20: 14726 | G20: 12292
A21: Depreciation/Amortization | C21: -- | D21: -- | E21: -- | F21: -- | G21: --
A22: Interest Expense, Net - Operating | C22: -- | D22: -- | E22: -- | F22: -- | G22: --
A23: Interest/Investment Income - Operating | C23: -- | D23: -- | E23: -- | F23: -- | G23: --
A24: Interest Expense(Income) - Net Operating | C24: -- | D24: -- | E24: -- | F24: -- | G24: --
A25: Interest Exp.(Inc.),Net-Operating, Total | C25: -- | D25: -- | E25: -- | F25: -- | G25: --
A26: Unusual Expense (Income) | C26: 13 | D26: 133 | E26: 26 | F26: 47 | G26: 2400
A27: Restructuring Charge | C27: -- | D27: -- | E27: 0 | F27: 0 | G27: 306
A28: Impairment-Assets Held for Sale | C28: 13 | D28: 133 | E28: 26 | F28: 47 | G28: 55
A29: Other Unusual Expense (Income) | C29: -- | D29: -- | E29: -- | F29: -- | G29: 2039
A30: Other Operating Expenses, Total | C30: -- | D30: -- | E30: -- | F30: -- | G30: --
A31: Total Operating Expense | C31: 98185 | D31: 90189 | E31: 82910 | F31: 75349 | G31: 67601
A32: Operating Income | C32: 69903 | D32: 52826 | E32: 42933 | F32: 35011 | G32: 28970
A33: Interest Expense, Net Non-Operating | C33: -2346 | D33: -2591 | E33: -2686 | F33: -2733 | G33: -2222
A34: Interest Expense - Non-Operating | C34: -2346 | D34: -2591 | E34: -2686 | F34: -2733 | G34: -2222
A35: Interest/Invest Income - Non-Operating | C35: 3447 | D35: 2841 | E35: 3498 | F35: 4255 | G35: 3404
A36: Investment Income - Non-Operating | C36: 3447 | D36: 2841 | E36: 3498 | F36: 4255 | G36: 3404
A37: Interest Income(Exp), Net Non-Operating | C37: -- | D37: -- | E37: -- | F37: -- | G37: --
A38: Interest Inc.(Exp.),Net-Non-Op., Total | C38: 1101 | D38: 250 | E38: 812 | F38: 1522 | G38: 1182
A39: Gain (Loss) on Sale of Assets | C39: -- | D39: -- | E39: -- | F39: -- | G39: --
A40: Other, Net | C40: 98 | D40: -40 | E40: -57 | F40: -59 | G40: -251
A41: Other Non-Operating Income (Expense) | C41: 98 | D41: -40 | E41: -57 | F41: -59 | G41: -251
A42: Net Income Before Taxes | C42: 71102 | D42: 53036 | E42: 43688 | F42: 36474 | G42: 29901
A43: Provision for Income Taxes | C43: 9831 | D43: 8755 | E43: 4291 | F43: 6203 | G43: 4412
A44: Net Income After Taxes | C44: 61271 | D44: 44281 | E44: 39397 | F44: 30271 | G44: 25489
A45: Minority Interest | C45: -- | D45: -- | E45: -- | F45: -- | G45: --
A46: Equity In Affiliates | C46: -- | D46: -- | E46: -- | F46: -- | G46: --
A47: U.S. GAAP Adjustment | C47: -- | D47: -- | E47: -- | F47: -- | G47: --
A48: Net Income Before Extra. Items | C48: 61271 | D48: 44281 | E48: 39397 | F48: 30271 | G48: 25489
A50: Accounting Change | C50: -- | D50: -- | E50: -- | F50: -- | G50: --
A51: Discontinued Operations | C51: -- | D51: -- | E51: -- | F51: -- | G51: --
A52: Extraordinary Item | C52: -- | D52: 0 | E52: -157 | F52: -13700 | G52: --
A53: Tax on Extraordinary Items | C53: -- | D53: -- | E53: -- | F53: -- | G53: --
A54: Total Extraordinary Items | C54: -- | D54: 0 | E54: -157 | F54: -13700 | G54: --
A55: Net Income | C55: 61271 | D55: 44281 | E55: 39240 | F55: 16571 | G55: 25489
A57: Preferred Dividends | C57: -- | D57: -- | E57: -- | F57: -- | G57: --
A58: General Partners' Distributions | C58: -- | D58: -- | E58: -- | F58: -- | G58: --
A59: Miscellaneous Earnings Adjustment | C59: -- | D59: -- | E59: -- | F59: -- | G59: --
A60: Pro Forma Adjustment | C60: -- | D60: -- | E60: -- | F60: -- | G60: --
A61: Interest Adjustment - Primary EPS | C61: -- | D61: -- | E61: -- | F61: -- | G61: --
A62: Total Adjustments to Net Income | C62: -- | D62: -- | E62: -- | F62: -- | G62: --
A63: Income Available to Com Excl ExtraOrd | C63: 61271 | D63: 44281 | E63: 39397 | F63: 30271 | G63: 25489
A64: Income Available to Com Incl ExtraOrd | C64: 61271 | D64: 44281 | E64: 39240 | F64: 16571 | G64: 25489
A65: Basic Weighted Average Shares | C65: 7547 | D65: 7610 | E65: 7673 | F65: 7700 | G65: 7746
A66: Basic EPS Excluding Extraordinary Items | C66: 8.12 | D66: 5.82 | E66: 5.13 | F66: 3.93 | G66: 3.29
A67: Basic EPS Including Extraordinary Items | C67: 8.12 | D67: 5.82 | E67: 5.11 | F67: 2.15 | G67: 3.29
A68: Dilution Adjustment | C68: -- | D68: -- | E68: -- | F68: -- | G68: --
A69: Diluted Net Income | C69: 61271 | D69: 44281 | E69: 39240 | F69: 16571 | G69: 25489
A70: Diluted Weighted Average Shares | C70: 7608 | D70: 7683 | E70: 7753 | F70: 7794 | G70: 7832
A71: Diluted EPS Excluding ExtraOrd Items | C71: 8.05 | D71: 5.76 | E71: 5.08 | F71: 3.88 | G71: 3.25
A72: Diluted EPS Including ExtraOrd Items | C72: 8.05 | D72: 5.76 | E72: 5.06 | F72: 2.13 | G72: 3.25
A73: Supplemental ($ Millions)
A74: DPS - Common Stock Primary Issue | C74: 2.19 | D74: 1.99 | E74: 1.8 | F74: 1.65 | G74: 1.53
A75: Dividends per Share - Com Stock Issue 2 | C75: -- | D75: -- | E75: -- | F75: -- | G75: --
A76: Dividends per Share - Com Stock Issue 3 | C76: -- | D76: -- | E76: -- | F76: -- | G76: --
A77: Dividends per Share - Com Stock Issue 4 | C77: -- | D77: -- | E77: -- | F77: -- | G77: --
A78: Special DPS - Common Stock Primary Issue | C78: -- | D78: -- | E78: -- | F78: -- | G78: --
A79: Special DPS - Common Stock Issue 2 | C79: -- | D79: -- | E79: -- | F79: -- | G79: --
A80: Special DPS - Common Stock Issue 3 | C80: -- | D80: -- | E80: -- | F80: -- | G80: --
A81: Special DPS - Common Stock Issue 4 | C81: -- | D81: -- | E81: -- | F81: -- | G81: --
A82: Gross Dividends - Common Stock | C82: 16871 | D82: 15483 | E82: 14103 | F82: 12917 | G82: 12040
A83: Pro Forma Stock Compensation Expense | C83: -- | D83: -- | E83: -- | F83: -- | G83: --
A84: Net Income after Stock Based Comp. Exp. | C84: -- | D84: -- | E84: -- | F84: -- | G84: --
A85: Basic EPS after Stock Based Comp. Exp. | C85: -- | D85: -- | E85: -- | F85: -- | G85: --
A86: Diluted EPS after Stock Based Comp. Exp. | C86: -- | D86: -- | E86: -- | F86: -- | G86: --
A87: (Gain) Loss on Sale of Assets, Suppl. | C87: -- | D87: -- | E87: -- | F87: -- | G87: --
A88: Impairment-Assets Held for Sale, Suppl. | C88: -- | D88: -- | E88: -- | F88: -- | G88: --
A89: Impairment-Assets Held for Use, Suppl. | C89: -- | D89: 186 | E89: -- | F89: -- | G89: --
A90: Litigation Charge, Supplemental | C90: -- | D90: -- | E90: -- | F90: -- | G90: --
A91: Purchased R&D Written-Off, Supplemental | C91: -- | D91: -- | E91: -- | F91: -- | G91: --
A92: Restructuring Charge, Supplemental | C92: -- | D92: -- | E92: -- | F92: -- | G92: --
A93: Other Unusual Expense(Income), Suppl. | C93: -- | D93: -- | E93: -- | F93: -- | G93: 918
A94: Non-Recurring Items, Supplemental, Total | C94: -- | D94: 186 | E94: -- | F94: -- | G94: 918
A95: Total Special Items | C95: 13 | D95: 319 | E95: 26 | F95: 47 | G95: 3318
A96: Normalized Income Before Taxes | C96: 71115 | D96: 53355 | E96: 43714 | F96: 36521 | G96: 33219
A97: Effect of Special Items on Income Taxes | C97: 2 | D97: 53 | E97: 3 | F97: 8 | G97: 490
A98: Inc Tax Ex Impact of Sp Items | C98: 9833 | D98: 8808 | E98: 4294 | F98: 6211 | G98: 4902
A99: Normalized Income After Taxes | C99: 61282 | D99: 44547 | E99: 39420 | F99: 30310 | G99: 28317
A100: Normalized Inc. Avail to Com. | C100: 61282 | D100: 44547 | E100: 39420 | F100: 30310 | G100: 28317
A101: Basic Normalized EPS | C101: 8.12 | D101: 5.85 | E101: 5.14 | F101: 3.94 | G101: 3.66
A102: Diluted Normalized EPS | C102: 8.05 | D102: 5.8 | E102: 5.08 | F102: 3.89 | G102: 3.62
A103: EPS, Supplemental | C103: -- | D103: -- | E103: -- | F103: -- | G103: --
A104: Funds From Operations - REIT | C104: -- | D104: -- | E104: -- | F104: -- | G104: --
...

Sheet BS
A1: Microsoft Corp | Balance Sheet 10-Feb-2022 16:56
A3: Balance Sheet
A4: Annual Standardised in Millions of U.S. Dollars
B5: 2021 | C5: 2020 | D5: 2019 | E5: 2018 | F5: 2017
A6: Earnings Quality Score | B6: 86 | C6: 94 | D6: 85 | E6: 98 | F6: 88
A7: Period End Date | B7: 30-Jun-2021 | C7: 30-Jun-2020 | D7: 30-Jun-2019 | E7: 30-Jun-2018 | F7: 30-Jun-2017
A8: Original Announcement Date | B8: 27-Jul-2021 20:42 | C8: 22-Jul-2020 20:03 | D8: 18-Jul-2019 20:04 | E8: 19-Jul-2018 20:04 | F8: 19-Jul-2018 20:04
A9: Assets ($ Millions)
A10: Cash and Short Term Investments | B10: 130334 | C10: 136527 | D10: 133819 | E10: 133650 | F10: 132881
A11: Cash & Equivalents | B11: 14224 | C11: 13576 | D11: 11356 | E11: 11946 | F11: 7663
A12: Short Term Investments | B12: 116110 | C12: 122951 | D12: 122463 | E12: 121704 | F12: 125218
A13: Accounts Receivable - Trade, Net | B13: 38043 | C13: 32011 | D13: 29524 | E13: 26481 | F13: 22431
A14: Accounts Receivable - Trade, Gross | B14: 38794 | C14: 32799 | D14: 29935 | E14: 26858 | F14: 22776
A15: Provision for Doubtful Accounts | B15: -751 | C15: -788 | D15: -411 | E15: -377 | F15: -345
A16: Total Receivables, Net | B16: 38043 | C16: 32011 | D16: 29524 | E16: 26481 | F16: 22431
A17: Total Inventory | B17: 2636 | C17: 1895 | D17: 2063 | E17: 2662 | F17: 2181
A18: Inventories - Finished Goods | B18: 1367 | C18: 1112 | D18: 1611 | E18: 1953 | F18: 1239
A19: Inventories - Work In Progress | B19: 79 | C19: 83 | D19: 53 | E19: 54 | F19: 145
A20: Inventories - Raw Materials | B20: 1190 | C20: 700 | D20: 399 | E20: 655 | F20: 797
A21: Prepaid Expenses | B21: -- | C21: -- | D21: -- | E21: -- | F21: --
A22: Other Current Assets, Total | B22: 13393 | C22: 11482 | D22: 10146 | E22: 6869 | F22: 5203
A23: Other Current Assets | B23: 13393 | C23: 11482 | D23: 10146 | E23: 6869 | F23: 5203
A24: Total Current Assets | B24: 184406 | C24: 181915 | D24: 175552 | E24: 169662 | F24: 162696
A26: Property/Plant/Equipment, Total - Gross | B26: 122154 | C26: 96101 | D26: 79186 | E26: 65369 | F26: 54468
A27: Buildings - Gross | B27: 50812 | C27: 39482 | D27: 31604 | E27: 25339 | F27: 21348
A28: Land/Improvements - Gross | B28: 3660 | C28: 1823 | D28: 1540 | E28: 1254 | F28: 1107
A29: Machinery/Equipment - Gross | B29: 51250 | C29: 41261 | D29: 33823 | E29: 27633 | F29: 21414
A30: Other Property/Plant/Equipment - Gross | B30: 16432 | C30: 13535 | D30: 12219 | E30: 11143 | F30: 10599
A31: Property/Plant/Equipment, Total - Net | B31: 70803 | C31: 52904 | D31: 43856 | E31: 36146 | F31: 30289
A32: Accumulated Depreciation, Total | B32: -51351 | C32: -43197 | D32: -35330 | E32: -29223 | F32: -24179
A33: Goodwill, Net | B33: 49711 | C33: 43351 | D33: 42026 | E33: 35683 | F33: 35122
A34: Intangibles, Net | B34: 7800 | C34: 7038 | D34: 7750 | E34: 8053 | F34: 10106
... A43: Total Assets | B43: 333779 | C43: 301311 | D43: 286556 | E43: 258848 | F43: 250312
A45: Liabilities ($ Millions)
A46: Accounts Payable | B46: 15163 | C46: 12530 | D46: 9382 | E46: 8617 | F46: 7390
A47: Payable/Accrued | B47: -- | C47: -- | D47: -- | E47: -- | F47: --
A48: Accrued Expenses | B48: 12019 | C48: 9490 | D48: 8345 | E48: 7502 | F48: 5819
A49: Notes Payable/Short Term Debt | B49: 0 | C49: 0 | D49: 0 | E49: 0 | F49: 9072
A50: Current Port. of LT Debt/Capital Leases | B50: 8863 | C50: 4289 | D50: 5833 | E50: 4174 | F50: 1162
A51: Other Current liabilities, Total | B51: 52612 | C51: 46001 | D51: 45860 | E51: 38195 | F51: 32302
A52: Customer Advances | B52: 41525 | C52: 36000 | D52: 32676 | E52: 28905 | F52: 24013
A53: Income Taxes Payable | B53: 2174 | C53: 2130 | D53: 5665 | E53: 2121 | F53: 718
A54: Other Payables | B54: -- | C54: -- | D54: -- | E54: -- | F54: --
A55: Other Current Liabilities | B55: 8913 | C55: 7871 | D55: 7519 | E55: 7169 | F55: 7571
A56: Total Current Liabilities | B56: 88657 | C56: 72310 | D56: 69420 | E56: 58488 | F56: 55745
A58: Total Long Term Debt | B58: 61824 | C58: 68534 | D58: 72919 | E58: 76367 | F58: 78498
A59: Long Term Debt | B59: 50074 | C59: 59578 | D59: 66662 | E59: 72242 | F59: 76073
A60: Capital Lease Obligations | B60: 11750 | C60: 8956 | D60: 6257 | E60: 4125 | F60: 2425
A61: Total Debt | B61: 70687 | C61: 72823 | D61: 78752 | E61: 80541 | F61: 88732
A62: Deferred Income Tax | B62: 198 | C62: 204 | D62: 233 | E62: 541 | F62: 5734
A63: Deferred Income Tax - LT Liability | B63: 198 | C63: 204 | D63: 233 | E63: 541 | F63: 5734
A64: Minority Interest | B64: -- | C64: -- | D64: -- | E64: -- | F64: --
A65: Other Liabilities, Total | B65: 41112 | C65: 41959 | D65: 41654 | E65: 40734 | F65: 22624
A66: Other Long Term Liabilities | B66: 41112 | C66: 41959 | D66: 41654 | E66: 40734 | F66: 22624
A67: Total Liabilities | B67: 191791 | C67: 183007 | D67: 184226 | E67: 176130 | F67: 162601
A69: Shareholders Equity ($ Millions)
A70: Redeemable Preferred Stock, Total | B70: -- | C70: -- | D70: -- | E70: -- | F70: --
A71: Preferred Stock - Non Redeemable, Net | B71: -- | C71: -- | D71: -- | E71: -- | F71: --
A72: Common Stock, Total | B72: 46994 | C72: 47319 | D72: 49680 | E72: 47981 | F72: 48175
A73: Common Stock | B73: 46994 | C73: 47319 | D73: 49680 | E73: 47981 | F73: 48175
A74: Additional Paid-In Capital | B74: 36117 | C74: 33233 | D74: 28841 | E74: 23242 | F74: 21140
A75: Retained Earnings (Accumulated Deficit) | B75: 57055 | C75: 34566 | D75: 24150 | E75: 13682 | F75: 17769
A76: Treasury Stock - Common | B76: -- | C76: -- | D76: -- | E76: -- | F76: --
A77: ESOP Debt Guarantee | B77: -- | C77: -- | D77: -- | E77: -- | F77: --
A78: Unrealized Gain (Loss) | B78: 3222 | C78: 5478 | D78: 1488 | E78: -892 | F78: 1825
A79: Other Equity, Total | B79: -1400 | C79: -2292 | D79: -1828 | E79: -1295 | F79: -1198
A80: Translation Adjustment | B80: -1381 | C80: -2254 | D80: -1828 | E80: -1510 | F80: -1332
A81: Other Comprehensive Income | B81: -19 | C81: -38 | D81: 0 | E81: 215 | F81: 134
A82: Total Equity | B82: 141988 | C82: 118304 | D82: 102330 | E82: 82718 | F82: 87711
A84: Total Liabilities & Shareholders' Equity | B84: 333779 | C84: 301311 | D84: 286556 | E84: 258848 | F84: 250312
A86: Supplemental ($ Millions)
A87: Shares Outstanding - Common Issue 2 | B87: -- | C87: -- | D87: -- | E87: -- | F87: --
A88: Shares Outstanding - Common Issue 3 | B88: -- | C88: -- | D88: -- | E88: -- | F88: --
A89: Shares Outstanding - Common Issue 4 | B89: -- | C89: -- | D89: -- | E89: -- | F89: --
A90: Total Common Shares Outstanding | B90: 7519 | C90: 7571 | D90: 7643 | E90: 7677 | F90: 7708
A91: Shares Outs - Common Stock Primary Issue | B91: 7519 | C91: 7571 | D91: 7643 | E91: 7677 | F91: 7708
A92: Treas Shares - Common Stock Prmry Issue | B92: 0 | C92: 0 | D92: 0 | E92: 0 | F92: 0
A93: Treasury Shares - Common Issue 2 | B93: -- | C93: -- | D93: -- | E93: -- | F93: --
A94: Treasury Shares - Common Issue 3 | B94: -- | C94: -- | D94: -- | E94: -- | F94: --
A95: Treasury Shares - Common Issue 4 | B95: -- | C95: -- | D95: -- | E95: -- | F95: --
A96: Total Preferred Shares Outstanding | B96: -- | C96: -- | D96: -- | E96: -- | F96: --
A97: Treasury Shares - Preferred Issue 1 | B97: -- | C97: -- | D97: -- | E97: -- | F97: --
A98: Treasury Shares - Preferred Issue 2 | B98: -- | C98: -- | D98: -- | E98: -- | F98: --
A99: Treasury Shares - Preferred Issue 3 | B99: -- | C99: -- | D99: -- | E99: -- | F99: --
A100: Treasury Shares - Preferred Issue 4 | B100: -- | C100: -- | D100: -- | E100: -- | F100: --
A101: Treasury Shares - Preferred Issue 5 | B101: -- | C101: -- | D101: -- | E101: -- | F101: --
A102: Treasury Shares - Preferred Issue 6 | B102: -- | C102: -- | D102: -- | E102: -- | F102: --
A103: Minority Interest - Redeemable | B103: -- | C103: -- | D103: -- | E103: -- | F103: --
A104: Minority Interest - Non Redeemable | B104: -- | C104: -- | D104: -- | E104: -- | F104: --
A105: Total Equity & Minority Interest | B105: 141988 | C105: 118304 | D105: 102330 | E105: 82718 | F105: 87711
A106: Full-Time Employees | B106: 181000 | C106: 163000 | D106: 144000 | E106: 131000 | F106: 124000
A107: Part-Time Employees | B107: -- | C107: -- | D107: -- | E107: -- | F107: --
A108: Number of Common Shareholders | B108: 89291 | C108: 91674 | D108: 94069 | E108: 97535 | F108: 101825
A109: Other Property/Plant/Equipment - Net | B109: -- | C109: -- | D109: -- | E109: -- | F109: --
A110: Intangibles - Net | B110: -- | C110: -- | D110: -- | E110: -- | F110: --
A111: Goodwill - Net | B111: 49711 | C111: 43351 | D111: 42026 | E111: 35683 | F111: 35122
A112: Accumulated Goodwill Amortization Suppl. | B112: -- | C112: -- | D112: -- | E112: -- | F112: --
A113: Accumulated Intangible Amort, Suppl. | B113: 12175 | C113: 10721 | D113: 9389 | E113: 7883 | F113: 6561
A114: Wgt Avg Rem Lease Term (Yrs)-Oper Lease | B114: 8 | C114: 8 | D114: -- | E114: -- | F114: --
A115: Wgt Avg Rem Lease Term (Yrs)-Fin Lease | B115: 12 | C115: 13 | D115: -- | E115: -- | F115: --
...

Sheet Prices
I2: Daily Retuns (%)
C3: Dates | D3: MSFT | E3: SPX Index | F3: Volume (MSFT) | I3: MSFT | J3: SPX Index
C4: 43140 | D4: 88.18 | E4: 2619.55 | F4: 63499.1 | L4: Regression Beta (3Y Daily) | N4: =SLOPE(I5:I1047,J5:J1047) -> 1.1886839
C5: 43143 | D5: 89.13 | E5: 2656 | F5: 35720.3 | I5: =D5/D4-1 -> 0.010773418 | J5: =E5/E4-1 -> 0.013914604
C6: 43144 | D6: 89.83 | E6: 2662.94 | F6: 26407.7 | I6: =D6/D5-1 -> 0.0078536968 | J6: =E6/E5-1 -> 0.0026129518
C7: 43145 | D7: 90.81 | E7: 2698.63 | F7: 34960.9 | I7: =D7/D6-1 -> 0.010909496 | J7: =E7/E6-1 -> 0.01340248
C8: 43146 | D8: 92.66 | E8: 2731.2 | F8: 27823.9 | I8: =D8/D7-1 -> 0.020372206 | J8: =E8/E7-1 -> 0.012069087
C9: 43147 | D9: 92 | E9: 2732.22 | F9: 30596.9 | I9: =D9/D8-1 -> -0.0071228146 | J9: =E9/E8-1 -> 0.00037346221
C10: 43150 | D10: 92 | E10: 2732.22 | F10: #N/A | I10: =D10/D9-1 -> 0 | J10: =E10/E9-1 -> 0
C11: 43151 | D11: 92.72 | E11: 2716.26 | F11: 30911.7 | I11: =D11/D10-1 -> 0.007826087 | J11: =E11/E10-1 -> -0.0058414037
C12: 43152 | D12: 91.49 | E12: 2701.33 | F12: 26922.5 | I12: =D12/D11-1 -> -0.013265746 | J12: =E12/E11-1 -> -0.0054965283
C13: 43153 | D13: 91.73 | E13: 2703.96 | F13: 24392.8 | I13: =D13/D12-1 -> 0.0026232375 | J13: =E13/E12-1 -> 0.00097359449
C14: 43154 | D14: 94.06 | E14: 2747.3 | F14: 26329.2 | I14: =D14/D13-1 -> 0.025400632 | J14: =E14/E13-1 -> 0.016028344
C15: 43157 | D15: 95.42 | E15: 2779.6 | F15: 30199.8 | I15: =D15/D14-1 -> 0.014458856 | J15: =E15/E14-1 -> 0.011756998
C16: 43158 | D16: 94.2 | E16: 2744.28 | F16: 25869.1 | I16: =D16/D15-1 -> -0.01278558 | J16: =E16/E15-1 -> -0.012706864
C17: 43159 | D17: 93.77 | E17: 2713.83 | F17: 31167.3 | I17: =D17/D16-1 -> -0.0045647558 | J17: =E17/E16-1 -> -0.011095807
C18: 43160 | D18: 92.85 | E18: 2677.67 | F18: 37135.6 | I18: =D18/D17-1 -> -0.0098112403 | J18: =E18/E17-1 -> -0.013324342
C19: 43161 | D19: 93.05 | E19: 2691.25 | F19: 32830.4 | I19: =D19/D18-1 -> 0.0021540118 | J19: =E19/E18-1 -> 0.0050715734
C20: 43164 | D20: 93.64 | E20: 2720.94 | F20: 23901.6 | I20: =D20/D19-1 -> 0.0063406771 | J20: =E20/E19-1 -> 0.011032048
C21: 43165 | D21: 93.32 | E21: 2728.12 | F21: 22175.8 | I21: =D21/D20-1 -> -0.003417343 | J21: =E21/E20-1 -> 0.0026387939
C22: 43166 | D22: 93.86 | E22: 2726.8 | F22: 26716.1 | I22: =D22/D21-1 -> 0.0057865409 | J22: =E22/E21-1 -> -0.00048384968
... C38: 43188 | D38: 91.27 | E38: 2640.87 | F38: 45867.5 | I38: =D38/D37-1 -> 0.021031435 | J38: =E38/E37-1 -> 0.013769674
C39: 43189 | D39: 91.27 | E39: 2640.87 | F39: #N/A | I39: =D39/D38-1 -> 0 | J39: =E39/E38-1 -> 0
C40: 43192 | D40: 88.52 | E40: 2581.88 | F40: 48515.4 | I40: =D40/D39-1 -> -0.030130382 | J40: =E40/E39-1 -> -0.022337336
C41: 43193 | D41: 89.71 | E41: 2614.45 | F41: 37213.8 | I41: =D41/D40-1 -> 0.01344329 | J41: =E41/E40-1 -> 0.012614839
C42: 43194 | D42: 92.33 | E42: 2644.69 | F42: 35560 | I42: =D42/D41-1 -> 0.029205217 | J42: =E42/E41-1 -> 0.011566486
C43: 43195 | D43: 92.38 | E43: 2662.84 | F43: 29771.9 | I43: =D43/D42-1 -> 0.0005415358 | J43: =E43/E42-1 -> 0.0068628081
C44: 43196 | D44: 90.23 | E44: 2604.47 | F44: 38026 | I44: =D44/D43-1 -> -0.023273436 | J44: =E44/E43-1 -> -0.021920205
C45: 43199 | D45: 90.77 | E45: 2613.16 | F45: 31533.9 | I45: =D45/D44-1 -> 0.0059847058 | J45: =E45/E44-1 -> 0.0033365714
C46: 43200 | D46: 92.88 | E46: 2656.87 | F46: 26939.9 | I46: =D46/D45-1 -> 0.023245566 | J46: =E46/E45-1 -> 0.016726875
C47: 43201 | D47: 91.86 | E47: 2642.19 | F47: 24872.1 | I47: =D47/D46-1 -> -0.010981912 | J47: =E47/E46-1 -> -0.0055252986
C48: 43202 | D48: 93.58 | E48: 2663.99 | F48: 26758.9 | I48: =D48/D47-1 -> 0.018724145 | J48: =E48/E47-1 -> 0.0082507314
C49: 43203 | D49: 93.08 | E49: 2656.3 | F49: 23346.1 | I49: =D49/D48-1 -> -0.005343022 | J49: =E49/E48-1 -> -0.0028866475
C50: 43206 | D50: 94.17 | E50: 2677.84 | F50: 20288.1 | I50: =D50/D49-1 -> 0.011710357 | J50: =E50/E49-1 -> 0.0081090238
C51: 43207 | D51: 96.07 | E51: 2706.39 | F51: 26771 | I51: =D51/D50-1 -> 0.020176277 | J51: =E51/E50-1 -> 0.010661578
... C79: 43245 | D79: 98.36 | E79: 2721.33 | F79: 18363.9 | I79: =D79/D78-1 -> 0.00050859526 | J79: =E79/E78-1 -> -0.0023572455
C80: 43248 | D80: 98.36 | E80: 2721.33 | F80: #N/A | I80: =D80/D79-1 -> 0 | J80: =E80/E79-1 -> 0
C81: 43249 | D81: 98.01 | E81: 2689.86 | F81: 28671 | I81: =D81/D80-1 -> -0.0035583571 | J81: =E81/E80-1 -> -0.011564198
C82: 43250 | D82: 98.95 | E82: 2724.01 | F82: 22158.5 | I82: =D82/D81-1 -> 0.0095908581 | J82: =E82/E81-1 -> 0.012695828
C83: 43251 | D83: 98.84 | E83: 2705.27 | F83: 34140.9 | I83: =D83/D82-1 -> -0.0011116726 | J83: =E83/E82-1 -> -0.0068795636
C84: 43252 | D84: 100.79 | E84: 2734.62 | F84: 28655.6 | I84: =D84/D83-1 -> 0.019728855 | J84: =E84/E83-1 -> 0.010849194
C85: 43255 | D85: 101.67 | E85: 2746.87 | F85: 27281.6 | I85: =D85/D84-1 -> 0.0087310249 | J85: =E85/E84-1 -> 0.0044795986
C86: 43256 | D86: 102.19 | E86: 2748.8 | F86: 23514.4 | I86: =D86/D85-1 -> 0.0051145864 | J86: =E86/E85-1 -> 0.00070261789
C87: 43257 | D87: 102.49 | E87: 2772.35 | F87: 21122.9 | I87: =D87/D86-1 -> 0.002935708 | J87: =E87/E86-1 -> 0.0085673749
C88: 43258 | D88: 100.88 | E88: 2770.37 | F88: 28232.2 | I88: =D88/D87-1 -> -0.01570885 | J88: =E88/E87-1 -> -0.00071419554
C89: 43259 | D89: 101.63 | E89: 2779.03 | F89: 22165.1 | I89: =D89/D88-1 -> 0.0074345757 | J89: =E89/E88-1 -> 0.0031259362
C90: 43262 | D90: 101.05 | E90: 2782 | F90: 23490.9 | I90: =D90/D89-1 -> -0.0057069763 | J90: =E90/E89-1 -> 0.0010687182
C91: 43263 | D91: 101.31 | E91: 2786.85 | F91: 18325.2 | I91: =D91/D90-1 -> 0.0025729837 | J91: =E91/E90-1 -> 0.0017433501
C92: 43264 | D92: 100.85 | E92: 2775.63 | F92: 29492.9 | I92: =D92/D91-1 -> -0.0045405192 | J92: =E92/E91-1 -> -0.0040260509
... C106: 43284 | D106: 99.05 | E106: 2713.22 | F106: 14670.3 | I106: =D106/D105-1 -> -0.0095990401 | J106: =E106/E105-1 -> -0.0049473541
C107: 43285 | D107: 99.05 | E107: 2713.22 | F107: #N/A | I107: =D107/D106-1 -> 0 | J107: =E107/E106-1 -> 0
C108: 43286 | D108: 99.76 | E108: 2736.61 | F108: 18977.4 | I108: =D108/D107-1 -> 0.0071680969 | J108: =E108/E107-1 -> 0.0086207532
C109: 43287 | D109: 101.16 | E109: 2759.82 | F109: 19234.6 | I109: =D109/D108-1 -> 0.014033681 | J109: =E109/E108-1 -> 0.0084812962
C110: 43290 | D110: 101.85 | E110: 2784.17 | F110: 18212 | I110: =D110/D109-1 -> 0.0068208778 | J110: =E110/E109-1 -> 0.0088230392
C111: 43291 | D111: 102.12 | E111: 2793.84 | F111: 19293.1 | I111: =D111/D110-1 -> 0.0026509573 | J111: =E111/E110-1 -> 0.0034732075
C112: 43292 | D112: 101.98 | E112: 2774.02 | F112: 19644.6 | I112: =D112/D111-1 -> -0.0013709362 | J112: =E112/E111-1 -> -0.0070941786
C113: 43293 | D113: 104.19 | E113: 2798.29 | F113: 24335.9 | I113: =D113/D112-1 -> 0.021670916 | J113: =E113/E112-1 -> 0.0087490357
C114: 43294 | D114: 105.43 | E114: 2801.31 | F114: 24653.5 | I114: =D114/D113-1 -> 0.011901334 | J114: =E114/E113-1 -> 0.0010792305
C115: 43297 | D115: 104.91 | E115: 2798.43 | F115: 21786.9 | I115: =D115/D114-1 -> -0.0049321825 | J115: =E115/E114-1 -> -0.0010280904
C116: 43298 | D116: 105.95 | E116: 2809.55 | F116: 25901.7 | I116: =D116/D115-1 -> 0.009913259 | J116: =E116/E115-1 -> 0.0039736567
C117: 43299 | D117: 105.12 | E117: 2815.62 | F117: 29493.9 | I117: =D117/D116-1 -> -0.0078338839 | J117: =E117/E116-1 -> 0.0021604883
C118: 43300 | D118: 104.4 | E118: 2804.49 | F118: 40171.6 | I118: =D118/D117-1 -> -0.0068493151 | J118: =E118/E117-1 -> -0.0039529482
C119: 43301 | D119: 106.27 | E119: 2801.83 | F119: 56038.8 | I119: =D119/D118-1 -> 0.017911877 | J119: =E119/E118-1 -> -0.00094847905
... C149: 43343 | D149: 112.33 | E149: 2901.52 | F149: 23222.7 | I149: =D149/D148-1 -> 0.0033943725 | J149: =E149/E148-1 -> 0.00013443038
C150: 43346 | D150: 112.33 | E150: 2901.52 | F150: #N/A | I150: =D150/D149-1 -> 0 | J150: =E150/E149-1 -> 0
C151: 43347 | D151: 111.71 | E151: 2896.72 | F151: 22634.6 | I151: =D151/D150-1 -> -0.0055194516 | J151: =E151/E150-1 -> -0.0016543053
C152: 43348 | D152: 108.49 | E152: 2888.6 | F152: 32872.4 | I152: =D152/D151-1 -> -0.028824635 | J152: =E152/E151-1 -> -0.0028031705
C153: 43349 | D153: 108.74 | E153: 2878.05 | F153: 23477.6 | I153: =D153/D152-1 -> 0.0023043598 | J153: =E153/E152-1 -> -0.0036522883
C154: 43350 | D154: 108.21 | E154: 2871.68 | F154: 22498.6 | I154: =D154/D153-1 -> -0.0048740114 | J154: =E154/E153-1 -> -0.0022133041
C155: 43353 | D155: 109.38 | E155: 2877.13 | F155: 20727.9 | I155: =D155/D154-1 -> 0.010812309 | J155: =E155/E154-1 -> 0.0018978438
C156: 43354 | D156: 111.24 | E156: 2887.89 | F156: 24301.8 | I156: =D156/D155-1 -> 0.017004937 | J156: =E156/E155-1 -> 0.003739838
C157: 43355 | D157: 111.71 | E157: 2888.92 | F157: 18891.1 | I157: =D157/D156-1 -> 0.0042250989 | J157: =E157/E156-1 -> 0.00035666178
C158: 43356 | D158: 112.91 | E158: 2904.18 | F158: 26055.6 | I158: =D158/D157-1 -> 0.0107421 | J158: =E158/E157-1 -> 0.0052822508
C159: 43357 | D159: 113.37 | E159: 2904.98 | F159: 19122.3 | I159: =D159/D158-1 -> 0.0040740413 | J159: =E159/E158-1 -> 0.00027546502
C160: 43360 | D160: 112.14 | E160: 2888.8 | F160: 20736.5 | I160: =D160/D159-1 -> -0.010849431 | J160: =E160/E159-1 -> -0.0055697457
C161: 43361 | D161: 113.21 | E161: 2904.31 | F161: 22170.9 | I161: =D161/D160-1 -> 0.0095416444 | J161: =E161/E160-1 -> 0.0053690114
C162: 43362 | D162: 111.7 | E162: 2907.95 | F162: 21728.4 | I162: =D162/D161-1 -> -0.013338044 | J162: =E162/E161-1 -> 0.0012533097
... C207: 43425 | D207: 103.11 | E207: 2649.93 | F207: 28130.6 | I207: =D207/D206-1 -> 0.013764625 | J207: =E207/E206-1 -> 0.0030432758
C208: 43426 | D208: 103.11 | E208: 2649.93 | F208: #N/A | I208: =D208/D207-1 -> 0 | J208: =E208/E207-1 -> 0
C209: 43427 | D209: 103.07 | E209: 2632.56 | F209: 13823.1 | I209: =D209/D208-1 -> -0.00038793521 | J209: =E209/E208-1 -> -0.0065548901
C210: 43430 | D210: 106.47 | E210: 2673.45 | F210: 32336.2 | I210: =D210/D209-1 -> 0.03298729 | J210: =E210/E209-1 -> 0.01553241
C211: 43431 | D211: 107.14 | E211: 2682.17 | F211: 29124.5 | I211: =D211/D210-1 -> 0.0062928524 | J211: =E211/E210-1 -> 0.003261703
C212: 43432 | D212: 111.12 | E212: 2743.79 | F212: 46788.5 | I212: =D212/D211-1 -> 0.037147657 | J212: =E212/E211-1 -> 0.022973935
C213: 43433 | D213: 110.19 | E213: 2737.76 | F213: 28123.2 | I213: =D213/D212-1 -> -0.0083693305 | J213: =E213/E212-1 -> -0.0021976901
C214: 43434 | D214: 110.89 | E214: 2760.17 | F214: 33665.6 | I214: =D214/D213-1 -> 0.0063526636 | J214: =E214/E213-1 -> 0.0081855239
C215: 43437 | D215: 112.09 | E215: 2790.37 | F215: 34732.8 | I215: =D215/D214-1 -> 0.010821535 | J215: =E215/E214-1 -> 0.010941355
C216: 43438 | D216: 108.52 | E216: 2700.06 | F216: 45197 | I216: =D216/D215-1 -> -0.031849407 | J216: =E216/E215-1 -> -0.032364884
C217: 43439 | D217: 108.52 | E217: 2700.06 | F217: #N/A | I217: =D217/D216-1 -> 0 | J217: =E217/E216-1 -> 0
C218: 43440 | D218: 109.19 | E218: 2695.95 | F218: 49107.4 | I218: =D218/D217-1 -> 0.0061739771 | J218: =E218/E217-1 -> -0.0015221884
C219: 43441 | D219: 104.82 | E219: 2633.08 | F219: 45044.9 | I219: =D219/D218-1 -> -0.04002198 | J219: =E219/E218-1 -> -0.023320165
C220: 43444 | D220: 107.59 | E220: 2637.72 | F220: 40801.5 | I220: =D220/D219-1 -> 0.026426255 | J220: =E220/E219-1 -> 0.0017621948
C221: 43445 | D221: 108.59 | E221: 2636.78 | F221: 42381.9 | I221: =D221/D220-1 -> 0.0092945441 | J221: =E221/E220-1 -> -0.00035636838
C222: 43446 | D222: 109.08 | E222: 2651.07 | F222: 36183 | I222: =D222/D221-1 -> 0.004512386 | J222: =E222/E221-1 -> 0.0054194889
C223: 43447 | D223: 109.45 | E223: 2650.54 | F223: 31333.4 | I223: =D223/D222-1 -> 0.0033920059 | J223: =E223/E222-1 -> -0.00019991928
C224: 43448 | D224: 106.03 | E224: 2599.95 | F224: 47043.1 | I224: =D224/D223-1 -> -0.031247145 | J224: =E224/E223-1 -> -0.019086677
C225: 43451 | D225: 102.89 | E225: 2545.94 | F225: 56957.3 | I225: =D225/D224-1 -> -0.02961426 | J225: =E225/E224-1 -> -0.020773476
C226: 43452 | D226: 103.97 | E226: 2546.16 | F226: 49319.2 | I226: =D226/D225-1 -> 0.010496647 | J226: =E226/E225-1 -> 8.6412091e-05
C227: 43453 | D227: 103.69 | E227: 2506.96 | F227: 68198.2 | I227: =D227/D226-1 -> -0.0026930845 | J227: =E227/E226-1 -> -0.015395733
C228: 43454 | D228: 101.51 | E228: 2467.42 | F228: 70334.2 | I228: =D228/D227-1 -> -0.021024207 | J228: =E228/E227-1 -> -0.015772091
C229: 43455 | D229: 98.23 | E229: 2416.62 | F229: 111242.1 | I229: =D229/D228-1 -> -0.032312087 | J229: =E229/E228-1 -> -0.020588307
...

Sheet Questions
E1: Total time to complete the test: 90min
D2: 1 | E2: From the statements provided (Tabs: "IS" and "BS") calculate the following. (Use excel linkings to show calculations and average data over the period for BS)
F4: FY2021 | G4: FY2020 | H4: FY2019 | I4: FY2018
E5: Asset Turnover | F5: =IS!C9/((BS!C43+BS!B43)/2) -> 0.529336 | G5: =IS!D9/((BS!D43+BS!C43)/2) -> 0.48655563 | H5: =IS!E9/((BS!E43+BS!D43)/2) -> 0.4614671 | I5: =IS!F9/((BS!F43+BS!E43)/2) -> 0.43349831
E6: Quick Ratio | F6: =(BS!B10+BS!B13)/BS!B56 -> 1.8991958 | G6: =(BS!C10+BS!C13)/BS!C56 -> 2.3307703 | H6: =(BS!D10+BS!D13)/BS!D56 -> 2.3529674 | I6: =(BS!E10+BS!E13)/BS!E56 -> 2.7378437
E7: Times Interest Earned | F7: =IS!C32/ABS(IS!C33+IS!C112) -> 35.664796 | G7: =IS!D32/ABS(IS!D33+IS!D112) -> 23.426164 | H7: =IS!E32/ABS(IS!E33+IS!E112) -> 17.602706 | I7: =IS!F32/ABS(IS!F33+IS!F112) -> 13.686865
E8: Cash Cycle | F8: =F14+F15-F16 -> -4.8681591 | G8: =G14+G15-G16 -> 7.4142276 | H8: =H14+H15-H16 -> 24.764067 | I8: =I14+I15-I16 -> 27.761647
E10: Inventory Turnover | F10: =IS!C13/((BS!B17+BS!C17)/2) -> 23.055396 | G10: =IS!D13/((BS!C17+BS!D17)/2) -> 23.283477 | H10: =IS!E13/((BS!D17+BS!E17)/2) -> 18.162963 | I10: =IS!F13/((BS!E17+BS!F17)/2) -> 15.83853
E11: Receivables Turnover | F11: =IS!C9/((BS!B16+BS!C16)/2) -> 4.7988123 | G11: =IS!D9/((BS!C16+BS!D16)/2) -> 4.648249 | H11: =IS!E9/((BS!D16+BS!E16)/2) -> 4.4939916 | I11: =IS!F9/((BS!E16+BS!F16)/2) -> 4.512594
E12: Payable Turnover | F12: =IS!C13/((BS!B46+BS!C46)/2) -> 3.7722168 | G12: =IS!D13/((BS!C46+BS!D46)/2) -> 4.205732 | H12: =IS!E13/((BS!D46+BS!E46)/2) -> 4.7680427 | I12: =IS!F13/((BS!E46+BS!F46)/2) -> 4.7920285
E14: Days of Sale O/s | F14: =365/F10 -> 15.831435 | G14: =365/G10 -> 15.676353 | H14: =365/H10 -> 20.09584 | I14: =365/I10 -> 23.045068
E15: Days of Inv on Hand | F15: =365/F11 -> 76.060486 | G15: =365/G11 -> 78.524193 | H15: =365/H11 -> 81.219555 | I15: =365/I11 -> 80.884741
E16: Days of Payable | F16: =365/F12 -> 96.76008 | G16: =365/G12 -> 86.786319 | H16: =365/H12 -> 76.551328 | I16: =365/I12 -> 76.168162
D18: 2 | E18: Calculate 3 year daily beta using the prices provided in tab "Prices" . Show the required working in "Prices" tab after Column H.
D20: 3 | E20: Populate a Price Line Chart (in single chart) for both Microsoft & S&P 500 Index using price data provided in "Prices" tab. Plot the same in "Prices" tab.
D22: 4 | E22: Populate a Price Line Chart and volume bar chart (in single chart) using price data provided. Plot the same in "Prices" tab.
D24: 5 | E24: Calculate YTD, QTD, MTD, WTD price performances (returns) for Microsoft based on the date mentioned in Cell E18, please make the calculations dynamic using excel. Use data in "Prices" tab.
E26: 44507 | F26: YTD | G26: QTD | H26: MTD | I26: WTD
E27: Date | F27: =Prices!C759 -> 44197 | G27: =Prices!C954 -> 44470 | H27: =Prices!C975 -> 44501 | I27: =Prices!C975 -> 44501
E28: Returns | F28: =(Prices!$D$979-Prices!D759)/Prices!D759 -> 0.51092573 | G28: =(Prices!D979-Prices!D956)/Prices!D954 -> 0.1636115 | H28: =(Prices!D979-Prices!D975)/Prices!D975 -> 0.020311498 | I28: =(Prices!D979-Prices!D975)/Prices!D975 -> 0.020311498
D30: 6 | E30: Concatenate the following two words with a space in between as a delimiter
E31: Robert | F31: Smith
E32: Answer | F32: =CONCATENATE(E31," ",F31) -> Robert Smith
D34: 7 | E34: Transpose the below data in space provided
K35: Please use excel function to do this
E36: Dates | F36: MSFT.O | G36: .SPX | J36: Answer: | K36: {=TRANSPOSE(E36:E45)} -> Dates | L36: 43140 | M36: 43143 | N36: 43144 | O36: 43145 | P36: 43146 | Q36: 43147 | R36: 43150 | S36: 43151 | T36: 43152
E37: 43140 | F37: 88.18 | G37: 2619.55 | K37: {=TRANSPOSE(F36:F45)} -> MSFT.O | L37: 88.18 | M37: 89.13 | N37: 89.83 | O37: 90.81 | P37: 92.66 | Q37: 92 | R37: 92 | S37: 92.72 | T37: 91.49
E38: 43143 | F38: 89.13 | G38: 2656 | K38: {=TRANSPOSE(G36:G45)} -> .SPX | L38: 2619.55 | M38: 2656 | N38: 2662.94 | O38: 2698.63 | P38: 2731.2 | Q38: 2732.22 | R38: 2732.22 | S38: 2716.26 | T38: 2701.33
E39: 43144 | F39: 89.83 | G39: 2662.94
E40: 43145 | F40: 90.81 | G40: 2698.63
E41: 43146 | F41: 92.66 | G41: 2731.2
E42: 43147 | F42: 92 | G42: 2732.22
E43: 43150 | F43: 92 | G43: 2732.22
E44: 43151 | F44: 92.72 | G44: 2716.26
E45: 43152 | F45: 91.49 | G45: 2701.33
D47: 8 | E47: Please use the below assumptions to answer the questions asked below
E48: Values for subject firm | H48: Values for peer group
E49: 5-year EPS growth rate | F49: 0.08 | H49: Median P/E | I49: 9
E50: Consensus EPS forecast | F50: 4.5 | H50: Median PEG | I50: 1.6
E51: Current stock price | F51: 28
E53: Calculating the PEG
E54: P/E for subject firm | F54: =F51/F50 -> 6.2222222
E55: PEG for subject firm | F55: =F54/F49 -> 77.777778
D57: 9 | E57: Calculate the price of a bond which has a par value of Rs 1000 and coupon payment is 10% and the yield is 8%. The maturity of a bond is 5 years.
E59: Par Value | F59: 1000 | H59: PV of CF year | I59: 1 | J59: =($F$59*$F$60)/(1+$F$63)^I59 -> 92.592593
E60: Coupon | F60: 0.1 | H60: PV of CF year | I60: =I59+1 -> 2 | J60: =($F$59*$F$60)/(1+$F$63)^I60 -> 85.733882
E61: Maturity | F61: 5 | H61: PV of CF year | I61: =I60+1 -> 3 | J61: =($F$59*$F$60)/(1+$F$63)^I61 -> 79.383224
E62: Payments | F62: 1 per year | H62: PV of CF year | I62: =I61+1 -> 4 | J62: =($F$59*$F$60)/(1+$F$63)^I62 -> 73.502985
E63: Yield | F63: 0.08 | H63: PV of CF year | I63: =I62+1 -> 5 | J63: =($F$59*$F$60)/(1+$F$63)^I63 -> 68.05832
H64: PV of Par Value | J64: =F59/(1+F63)^I63 -> 680.5832
H65: PV of Bond | J65: =SUM(J59:J64) -> 1079.8542
